{
  "bloodhound": "ブラッドハウンド",
  "gibraltar": "ジブラルタル",
  "lifeline": "ライフライン",
  "pathfinder": "パスファインダー",
  "wraith": "レイス",
  "bangalore": "バンガロール",
  "coustic": "コースティック",
  "mirage": "ミラージュ",
  "octane": "オクタン",
  "wattson": "ワットソン",
  "crypto": "クリプト",
  "revenant": "レヴナント",
  "loba": "ローバ",
  "rampart": "ランパート",
  "horizon": "ホライゾン",
  "fuse": "ヒューズ",
  "valkyrie": "ヴァルキリー",
  "seer": "シア",
  "ash": "アッシュ",
  "madmaggie": "マッドマギー",
  "newcastle": "ニューキャッスル",
  "energy": "ハボック",
  "flatline": "フラットライン",
  "hemlok": "ヘムロック",
  "r301": "R-301",
  "alternator": "オルタネーター",
  "prower": "プラウラー",
  "r99": "R-99",
  "volt": "ボルトSMG",
  "car": "C.A.R.",
  "devotion": "ディボーション",
  "spitfire": "スピットファイア",
  "lstar": "Lスター",
  "rampage": "ランページ",
  "g7": "G7スカウト",
  "tripletake": "トリプルテイク",
  "3030": "30-30リピーター",
  "bocek": "ボセック",
  "chargerifle": "チャージライフル",
  "longbow": "ロングボウ",
  "kraber": "クレーバー",
  "sentinel": "センチネル",
  "eva": "EVA-8",
  "mastiff": "マスティフ",
  "mozambique": "モザンビーク",
  "peacekeeper": "ピースキーパー",
  "re45": "RE-45",
  "p2020": "P2020",
  "wingman": "ウィングマン"
}
